helper_functions.py
CalculatingFeatures/__init__.py
CalculatingFeatures/acceleration_mapper.py
CalculatingFeatures/calculate_acc_gyro_common_features.py
CalculatingFeatures/calculate_fast.py
CalculatingFeatures/calculate_features.py
CalculatingFeatures/calculate_hrv_peaks.py
CalculatingFeatures/common_mapper.py
CalculatingFeatures/feature_functions.py
CalculatingFeatures/feature_functions_fast.py
CalculatingFeatures/gsr.py
CalculatingFeatures/gyro_mapper.py
CalculatingFeatures/helper_functions.py
CalculatingFeatures/hrv.py
CalculatingFeatures/pipeline_functions.py
cr_features/__init__.py
cr_features/acceleration_mapper.py
cr_features/calculate_acc_gyro_common_features.py
cr_features/calculate_features.py
cr_features/calculate_features_old.py
cr_features/calculate_hrv_peaks.py
cr_features/common_mapper.py
cr_features/feature_functions.py
cr_features/feature_functions_fast.py
cr_features/gsr.py
cr_features/gyro_mapper.py
cr_features/helper_functions.py
cr_features/hrv.py
cr_features/pipeline_functions.py
cr_features/eda_explorer/AccelerometerFeatureExtractionScript.py
cr_features/eda_explorer/ArtifactClassifiers.py
cr_features/eda_explorer/EDA-Artifact-Detection-Script.py
cr_features/eda_explorer/EDA_Peak_Detection_Script.py
cr_features/eda_explorer/__init__.py
cr_features/eda_explorer/classify.py
cr_features/eda_explorer/load_files.py
cr_features-0.1.6.dist-info/LICENSE.txt
cr_features-0.1.6.dist-info/METADATA
cr_features-0.1.6.dist-info/WHEEL
cr_features-0.1.6.dist-info/top_level.txt
cr_features-0.1.6.dist-info/RECORD
