Metadata-Version: 2.1
Name: cr-features
Version: 0.1.6
Summary: A library for calculating features suitable for context recognition
Home-page: UNKNOWN
Author: Department of Intelligent Systems, Jožef Stefan Institute
Author-email: vito.janko@ijs.si
License: MIT
Platform: UNKNOWN
Requires-Dist: biosppy
Requires-Dist: hmmlearn
Requires-Dist: numpy
Requires-Dist: pandas
Requires-Dist: PeakUtils
Requires-Dist: scikit-learn
Requires-Dist: scipy
Requires-Dist: tqdm
Requires-Dist: PyWavelets
